pawan/__init__.py
pawan/a1.py
pawan/a2.py
pawan-0.0.1.dist-info/LICENSE
pawan-0.0.1.dist-info/METADATA
pawan-0.0.1.dist-info/WHEEL
pawan-0.0.1.dist-info/top_level.txt
pawan-0.0.1.dist-info/RECORD
