Metadata-Version: 2.1
Name: pawan
Version: 0.0.1
Summary: pawan
Author: Pawan
Author-email: pawan1995219@gmail.com
Keywords: arithmetic,math,mathematics,python tutorial,pawan sharma
Classifier: Development Status :: 1 - Planning
Classifier: Intended Audience :: Developers
Classifier: Programming Language :: Python :: 3
Classifier: Operating System :: Unix
Classifier: Operating System :: MacOS :: MacOS X
Classifier: Operating System :: Microsoft :: Windows
License-File: LICENSE
